protowhat/Feedback.py
protowhat/Reporter.py
protowhat/State.py
protowhat/Test.py
protowhat/__init__.py
protowhat/failure.py
protowhat/sct_context.py
protowhat/sct_syntax.py
protowhat/selectors.py
protowhat/utils.py
protowhat/utils_ast.py
protowhat/utils_messaging.py
protowhat/checks/__init__.py
protowhat/checks/check_bash_history.py
protowhat/checks/check_files.py
protowhat/checks/check_funcs.py
protowhat/checks/check_logic.py
protowhat/checks/check_simple.py
protowhat-2.3.1.dist-info/licenses/LICENSE
protowhat-2.3.1.dist-info/METADATA
protowhat-2.3.1.dist-info/WHEEL
protowhat-2.3.1.dist-info/top_level.txt
protowhat-2.3.1.dist-info/RECORD
