Metadata-Version: 2.4
Name: protowhat
Version: 2.3.1
Summary: Prototype package for submission correctness testing
Home-page: https://github.com/datacamp/protowhat
Author: Filip Schouwenaars
Author-email: filip@datacamp.com
Maintainer: Jeroen Hermans
Maintainer-email: content-engineering@datacamp.com
Classifier: Programming Language :: Python :: 3
Classifier: License :: OSI Approved :: GNU Affero General Public License v3
Classifier: Operating System :: OS Independent
License-File: LICENSE
Requires-Dist: markdown2==2.5.3
Requires-Dist: jinja2==3.1.3
Dynamic: author
Dynamic: author-email
Dynamic: classifier
Dynamic: description
Dynamic: description-content-type
Dynamic: home-page
Dynamic: license-file
Dynamic: maintainer
Dynamic: maintainer-email
Dynamic: requires-dist
Dynamic: summary
